easy_pass/__init__.py
easy_pass/easy_pass.py
easy_pass-0.1.dist-info/LICENSE
easy_pass-0.1.dist-info/METADATA
easy_pass-0.1.dist-info/WHEEL
easy_pass-0.1.dist-info/top_level.txt
easy_pass-0.1.dist-info/RECORD
