Metadata-Version: 2.1
Name: easy-pass
Version: 0.1
Summary: A library to hash passwords and manage them.
Home-page: https://github.com/sahal-mulki
Author: Muhammad Sahal Mulki
Author-email: m.sahalmulki@gmail.com
License: MIT
Keywords: sha-256hash,password
Platform: UNKNOWN
Classifier: Development Status :: 4 - Beta
Classifier: Intended Audience :: Developers
Classifier: Topic :: Software Development :: Build Tools
Classifier: License :: OSI Approved :: MIT License
Classifier: Programming Language :: Python :: 3
Classifier: Programming Language :: Python :: 3.4
Classifier: Programming Language :: Python :: 3.5
Classifier: Programming Language :: Python :: 3.6
